valoStatus/Region.py
valoStatus/__init__.py
valoStatus-3.3.16.dist-info/LICENSE.txt
valoStatus-3.3.16.dist-info/METADATA
valoStatus-3.3.16.dist-info/WHEEL
valoStatus-3.3.16.dist-info/top_level.txt
valoStatus-3.3.16.dist-info/RECORD
