Metadata-Version: 2.1
Name: valoStatus
Version: 3.3.16
Summary: A python module to check for Riot Games server status for VALORANT without an API key
Home-page: https://github.com/D3CRYPT360/valoStatus
Author: D3CRYPT360
License: UNKNOWN
Keywords: valorant,gaming,gamers,riot,riotgames,VALORANT
Platform: UNKNOWN
Classifier: Programming Language :: Python :: 3
Classifier: License :: OSI Approved :: MIT License
Classifier: Operating System :: OS Independent
Requires-Python: >= 3.6
Requires-Dist: http.client
